nmtlab/__init__.py
nmtlab/dataset/__init__.py
nmtlab/dataset/base.py
nmtlab/dataset/bilingual_dataset.py
nmtlab/dataset/fixed_iterator.py
nmtlab/dataset/mt_dataset.py
nmtlab/decoding/__init__.py
nmtlab/decoding/beam_search.py
nmtlab/decoding/beam_translator.py
nmtlab/evaluation/__init__.py
nmtlab/evaluation/base.py
nmtlab/evaluation/moses_bleu.py
nmtlab/evaluation/sacre_bleu.py
nmtlab/evaluation/token_bleu.py
nmtlab/functions/__init__.py
nmtlab/functions/gelu.py
nmtlab/functions/residual.py
nmtlab/models/__init__.py
nmtlab/models/attention_model.py
nmtlab/models/deep_lstm.py
nmtlab/models/encoder_decoder.py
nmtlab/models/fast_deep_lstm.py
nmtlab/models/rnmt_plus.py
nmtlab/models/transformer.py
nmtlab/modules/__init__.py
nmtlab/modules/kv_attention.py
nmtlab/modules/multihead_attention.py
nmtlab/modules/transformer_modules.py
nmtlab/schedulers/__init__.py
nmtlab/schedulers/anneal.py
nmtlab/schedulers/base.py
nmtlab/schedulers/rmnt_plus_scheduler.py
nmtlab/schedulers/simple.py
nmtlab/schedulers/transformer_scheduler.py
nmtlab/trainers/__init__.py
nmtlab/trainers/adamsgd.py
nmtlab/trainers/base.py
nmtlab/trainers/distributed_optim.py
nmtlab/trainers/hvd_utils.py
nmtlab/trainers/trainer.py
nmtlab/utils/__init__.py
nmtlab/utils/bleu.py
nmtlab/utils/mapdict.py
nmtlab/utils/monitor.py
nmtlab/utils/multigpu.py
nmtlab/utils/opts.py
nmtlab/utils/tensormap.py
nmtlab/utils/vocab.py
test/__init__.py
test/test_attention.py
test/test_fixediterator.py
test/test_lazydict.py
test/test_rnmt_plus.py
test/test_sacrebleu.py
test/test_transformer.py
test/test_transformer_modules.py
nmtlab-0.7.4.dist-info/LICENSE
nmtlab-0.7.4.dist-info/METADATA
nmtlab-0.7.4.dist-info/WHEEL
nmtlab-0.7.4.dist-info/top_level.txt
nmtlab-0.7.4.dist-info/RECORD
